slack_api/__init__.py
slack_api/api.py
slack_api/exceptions.py
slack_api/user.py
slack_api/admin/__init__.py
slack_api/admin/users.py
jhulib_slack-0.0.4.20190720175743.dist-info/METADATA
jhulib_slack-0.0.4.20190720175743.dist-info/NOTICE.txt
jhulib_slack-0.0.4.20190720175743.dist-info/WHEEL
jhulib_slack-0.0.4.20190720175743.dist-info/top_level.txt
jhulib_slack-0.0.4.20190720175743.dist-info/RECORD
