Metadata-Version: 2.1
Name: jhulib-slack
Version: 0.0.4.20190720175743
Summary: A python implementation of the slack API including SCIM
Home-page: https://github.com/jhu-sheridan-libraries/python_slack_api
Author: Derek Belrose
Author-email: dbelrose@jhu.edu
License: Apache
Keywords: slack api scim
Platform: UNKNOWN
Requires-Dist: requests
